SQLess/SQLessKeywords.py
SQLess/__init__.py
SQLess/adapters/__init__.py
SQLess/adapters/adapter.py
SQLess/adapters/mysql.py
SQLess/adapters/oracle.py
SQLess/adapters/postgres.py
SQLess/adapters/sqlite.py
robotframework_sqless-0.1.0.dist-info/LICENSE
robotframework_sqless-0.1.0.dist-info/METADATA
robotframework_sqless-0.1.0.dist-info/WHEEL
robotframework_sqless-0.1.0.dist-info/top_level.txt
robotframework_sqless-0.1.0.dist-info/RECORD
