Metadata-Version: 2.1
Name: robotframework-sqless
Version: 0.1.0
Summary: robotframework-sqless is a SQL abstraction library for Robot Framework
Home-page: https://github.com/eternalconcert/robotframework-sqless
Author: Christian Kokoska
Author-email: info@softcreate.de
License: Apache License 2.0
Keywords: robotframework testing test automation http client sql orm postgres postgresql mysql sqlite
Platform: any
Requires-Dist: robotframework (>=3.1.2)
Requires-Dist: pyyaml (>=5.3)
Requires-Dist: nopea (>=0.0.4)
